jquantsapi/__init__.py
jquantsapi/client.py
dakimura_sample-0.0.1.dist-info/LICENSE
dakimura_sample-0.0.1.dist-info/WHEEL
dakimura_sample-0.0.1.dist-info/METADATA
dakimura_sample-0.0.1.dist-info/RECORD
