Metadata-Version: 2.1
Name: dakimura-sample
Version: 0.0.1
Summary: J-Quants API Client Library
License: Apache-2.0
Keywords: jquants,api,client,J-Quants
Author: dakimura
Author-email: dakimura@example.com
Requires-Python: >=3.7.1,<4.0
Classifier: License :: OSI Approved :: Apache Software License
Classifier: Operating System :: OS Independent
Classifier: Programming Language :: Python :: 3
Classifier: Programming Language :: Python :: 3.10
Classifier: Programming Language :: Python :: 3.8
Classifier: Programming Language :: Python :: 3.9
Requires-Dist: numpy (>=1.21.6,<1.22.0); python_full_version >= "3.7.1" and python_version < "3.8"
Requires-Dist: numpy (>=1.23.1,<2.0.0); python_version >= "3.8"
Requires-Dist: pandas (>=1.3.5,<1.4.0); python_full_version >= "3.7.1" and python_version < "3.8"
Requires-Dist: pandas (>=1.4.3,<2.0.0); python_version >= "3.8"
Requires-Dist: requests (>=2.28.1,<3.0.0)
Requires-Dist: types-python-dateutil (>=2.8.19,<3.0.0)
Requires-Dist: types-requests (>=2.28.5,<3.0.0)
